github_ai/__init__.py
github_ai/search.py
github_ai-1.0.1.dist-info/LICENSE
github_ai-1.0.1.dist-info/METADATA
github_ai-1.0.1.dist-info/WHEEL
github_ai-1.0.1.dist-info/top_level.txt
github_ai-1.0.1.dist-info/RECORD
