Metadata-Version: 2.1
Name: github-ai
Version: 1.0.1
Summary: A tool to search GitHub repositories using the GitHub API
Home-page: https://mrfidal.in/basic-pip-package/github-ai
Author: Fidal
Author-email: mrfidal@proton.me
Classifier: Programming Language :: Python :: 3
Classifier: License :: OSI Approved :: MIT License
Classifier: Operating System :: OS Independent
Requires-Python: >=3.6
License-File: LICENSE
Requires-Dist: requests
